gritql/README.md
gritql/__init__.py
gritql/installer.py
gritql/requirements.txt
gritql/run.py
gritql-0.1.4.dist-info/METADATA
gritql-0.1.4.dist-info/WHEEL
gritql-0.1.4.dist-info/RECORD
